ProcessCubeLibrary/ProcessCubeLibrary.py
ProcessCubeLibrary/__init__.py
ProcessCubeLibrary/docker_handler.py
ProcessCubeLibrary/keywords/__init__.py
ProcessCubeLibrary/keywords/_fields_helper.py
ProcessCubeLibrary/keywords/_retry_helper.py
ProcessCubeLibrary/keywords/deploy_keyword.py
ProcessCubeLibrary/keywords/empty_task_keyword.py
ProcessCubeLibrary/keywords/engine_keyword.py
ProcessCubeLibrary/keywords/external_task_keyword.py
ProcessCubeLibrary/keywords/manual_task_keyword.py
ProcessCubeLibrary/keywords/process_instance_keyword.py
ProcessCubeLibrary/keywords/send_keyword.py
ProcessCubeLibrary/keywords/start_keyword.py
ProcessCubeLibrary/keywords/user_task_keyword.py
robotframework_processcube-6.1.2.dist-info/METADATA
robotframework_processcube-6.1.2.dist-info/WHEEL
robotframework_processcube-6.1.2.dist-info/top_level.txt
robotframework_processcube-6.1.2.dist-info/RECORD
