Metadata-Version: 2.4
Name: robotframework-processcube
Version: 6.1.2
Summary: Robot Framework Keywords for processcube workflow engine.
Home-page: https://github.com/atlas-engine-contrib/robotframework-processcube
Author: 5Minds IT-Solutions GmbH & Co. KG
Author-email: processcube@5minds.de
License: MIT Licence
Classifier: Intended Audience :: Developers
Classifier: Natural Language :: English
Classifier: Programming Language :: Python :: 3
Classifier: Topic :: Software Development
Classifier: License :: OSI Approved :: Apache Software License
Classifier: Operating System :: OS Independent
Classifier: Development Status :: 5 - Production/Stable
Classifier: Framework :: Robot Framework
Requires-Dist: wheel==0.45.1
Requires-Dist: processcube-client==6.1.0
Requires-Dist: docker==7.1.0
Requires-Dist: requests>=2.32.0
Requires-Dist: robotframework>=7.3.2
Requires-Dist: six==1.17.0
Dynamic: author
Dynamic: author-email
Dynamic: classifier
Dynamic: description
Dynamic: description-content-type
Dynamic: home-page
Dynamic: license
Dynamic: requires-dist
Dynamic: summary
